chuk_gym_core/__init__.py
chuk_gym_core/py.typed
chuk_gym_core/curriculum/__init__.py
chuk_gym_core/curriculum/scheduler.py
chuk_gym_core/env/__init__.py
chuk_gym_core/env/base.py
chuk_gym_core/export/__init__.py
chuk_gym_core/export/formats.py
chuk_gym_core/export/jsonl.py
chuk_gym_core/generators/__init__.py
chuk_gym_core/generators/base.py
chuk_gym_core/schemas/__init__.py
chuk_gym_core/schemas/config.py
chuk_gym_core/schemas/episode.py
chuk_gym_core/schemas/problem.py
chuk_gym_core/schemas/trace.py
chuk_gym_core/schemas/verification.py
chuk_gym_core/verifiers/__init__.py
chuk_gym_core/verifiers/base.py
chuk_gym_core-0.1.1.dist-info/METADATA
chuk_gym_core-0.1.1.dist-info/WHEEL
chuk_gym_core-0.1.1.dist-info/RECORD
